kddl/__init__.py
kddl/_logging.py
kddl/datasets.py
kddl/gather.py
kddl/lrfind.py
kddl/lrfind2.py
kddl/nn.py
kddl/slurm.py
kddl/testing.py
kddl/train.py
kddl-0.0.2.dist-info/licenses/LICENSE
kddl-0.0.2.dist-info/METADATA
kddl-0.0.2.dist-info/WHEEL
kddl-0.0.2.dist-info/top_level.txt
kddl-0.0.2.dist-info/RECORD
